ip_country_search/__init__.py
ip_country_search/constants.py
ip_country_search/helpers.py
ip_country_search/main.py
ip_country_search/static/csv/afrinic.csv
ip_country_search/static/csv/apnic.csv
ip_country_search/static/csv/arin.csv
ip_country_search/static/csv/lacnic.csv
ip_country_search/static/csv/ripencc.csv
ip_country_search-1.0.1.dist-info/LICENSE.txt
ip_country_search-1.0.1.dist-info/METADATA
ip_country_search-1.0.1.dist-info/WHEEL
ip_country_search-1.0.1.dist-info/top_level.txt
ip_country_search-1.0.1.dist-info/RECORD
