Metadata-Version: 2.1
Name: ip-country-search
Version: 1.0.1
Summary: A python utility for searching country name for ipaddress
Home-page: https://github.com/manumathew23/ip-country-search
Author: Manu Mathew
Author-email: manumatew@gmail.com
License: LICENSE.txt
Download-URL: https://github.com/manumathew23/ip-country-search/archive/v1.0.1.tar.gz
Platform: UNKNOWN
Requires-Dist: certifi
Requires-Dist: chardet
Requires-Dist: idna
Requires-Dist: numpy
Requires-Dist: Pillow
Requires-Dist: requests
Requires-Dist: six
Requires-Dist: urllib3
